setup.py
file_readers/__init__.py
file_readers/data_collector.py
file_readers/file_reader.py
file_readers/metadata.py
file_readers.egg-info/PKG-INFO
file_readers.egg-info/SOURCES.txt
file_readers.egg-info/dependency_links.txt
file_readers.egg-info/requires.txt
file_readers.egg-info/top_level.txt
file_readers/csv/__init__.py
file_readers/csv/csv_filereader.py
file_readers/csv/csv_row_data_collector.py
file_readers/csv/tests/__init__.py
file_readers/csv/tests/test_csv_filereader.py
file_readers/csv/tests/test_csv_row_data_collector.py
file_readers/excel/__init__.py
file_readers/excel/default_excel_reader.py
file_readers/excel/excel_data_collector.py
file_readers/excel/excel_reader.py
file_readers/excel/simple_excel_data_collector.py
file_readers/excel/tests/__init__.py
file_readers/excel/tests/simple_cell.py
file_readers/excel/tests/test_default_excel_reader.py
file_readers/excel/tests/test_excel_data_collector.py
file_readers/excel/tests/test_excel_reader.py
file_readers/excel/tests/test_simple_excel_data_collector.py