Metadata-Version: 1.1
Name: file-readers
Version: 0.0.9
Summary: Library of different types of file reader and data collector classes.
Home-page: https://github.com/mjalas/file-readers
Author: Mats Jalas
Author-email: mats.jalas@gmail.com
License: MIT
Platform: UNKNOWN
Classifier: Development Status :: 3 - Alpha
Classifier: Intended Audience :: Developers
Classifier: Topic :: Software Development :: Libraries
Classifier: License :: OSI Approved :: MIT License
Classifier: Programming Language :: Python :: 3.5
